jnotype/__init__.py
jnotype/_csp.py
jnotype/_factor_analysis/__init__.py
jnotype/_factor_analysis/_gibbs_backend.py
jnotype/_factor_analysis/_inference.py
jnotype/_factor_analysis/_simulate.py
jnotype/_utils.py
jnotype/_variance.py
jnotype/bmm/__init__.py
jnotype/bmm/_em.py
jnotype/bmm/_gibbs.py
jnotype/checks/__init__.py
jnotype/checks/_histograms.py
jnotype/checks/_plots.py
jnotype/checks/_statistics.py
jnotype/conditional_bernoulli.py
jnotype/datasets/__init__.py
jnotype/datasets/_simulation/__init__.py
jnotype/datasets/_simulation/_block_images.py
jnotype/energy/__init__.py
jnotype/energy/_dfd.py
jnotype/energy/_prior.py
jnotype/energy/_sampling.py
jnotype/exclusivity/__init__.py
jnotype/exclusivity/_bernoulli_mixtures.py
jnotype/exclusivity/_full.py
jnotype/exclusivity/_independent.py
jnotype/exclusivity/_rigid.py
jnotype/gaussian/__init__.py
jnotype/gaussian/_horseshoe.py
jnotype/gaussian/_numeric.py
jnotype/gaussian/_spike_and_slab.py
jnotype/logistic/__init__.py
jnotype/logistic/_binary_latent.py
jnotype/logistic/_polyagamma.py
jnotype/logistic/_structure.py
jnotype/logistic/logreg.py
jnotype/pyramids/__init__.py
jnotype/pyramids/_sampler_csp.py
jnotype/pyramids/_sampler_fixed.py
jnotype/sampling/__init__.py
jnotype/sampling/_chunker.py
jnotype/sampling/_jax_loop.py
jnotype/sampling/_sampler.py
jnotype-0.1.0.dist-info/LICENSE
jnotype-0.1.0.dist-info/METADATA
jnotype-0.1.0.dist-info/WHEEL
jnotype-0.1.0.dist-info/RECORD
