Metadata-Version: 2.1
Name: jnotype
Version: 0.1.0
Summary: Jnotype: probabilistic modeling of high-dimensional binary data.
Author: Paweł Czyż
Requires-Python: >=3.9,<3.13
Classifier: Programming Language :: Python :: 3
Classifier: Programming Language :: Python :: 3.9
Classifier: Programming Language :: Python :: 3.10
Classifier: Programming Language :: Python :: 3.11
Requires-Dist: arviz (>=0.15.1,<0.16.0)
Requires-Dist: jax (>=0.4.6,<0.5.0)
Requires-Dist: jaxlib (>=0.4.6,<0.5.0)
Requires-Dist: jaxtyping (>=0.2.14,<0.3.0)
Requires-Dist: matplotlib (>=3.7.1,<4.0.0)
Requires-Dist: numpy (>=1.24.2,<2.0.0)
Requires-Dist: numpyro (>=0.15.3,<0.16.0)
Requires-Dist: polyagamma (>=1.3.5,<2.0.0)
Requires-Dist: tqdm (>=4.65.0,<5.0.0)
Requires-Dist: xarray (>=2023.3.0,<2024.0.0)
